rtyaml/__init__.py
rtyaml-1.0.0.dist-info/LICENSE
rtyaml-1.0.0.dist-info/METADATA
rtyaml-1.0.0.dist-info/WHEEL
rtyaml-1.0.0.dist-info/top_level.txt
rtyaml-1.0.0.dist-info/RECORD
