Metadata-Version: 2.1
Name: rtyaml
Version: 1.0.0
Summary: All the annoying things to make YAML usable in a source controlled environment.
Home-page: https://github.com/unitedstates/rtyaml
Author: Joshua Tauberer
Author-email: jt@occams.info
License: CC0 (copyright waived)
Platform: UNKNOWN
